figures/__init__.py
figures/line.py
figures/point.py
figures/triangle.py
geometry_alrandis-0.3.0.dist-info/METADATA
geometry_alrandis-0.3.0.dist-info/WHEEL
geometry_alrandis-0.3.0.dist-info/top_level.txt
geometry_alrandis-0.3.0.dist-info/RECORD
