Metadata-Version: 2.1
Name: geometry-alrandis
Version: 0.3.0
Summary: This  is very useful package
Author: me
Author-email: alrandisisdernii@gmail.com
